{
  "name": "Isotonic PII-200K (English subset)",
  "source": "Isotonic/pii-masking-200k",
  "samples": [
    {
      "text": "Bitte aktualisieren Sie Ihre 63828-1928 und 155 gem\u00e4\u00df den neuen gesetzlichen Bestimmungen.",
      "expected": "NONE",
      "source": "Isotonic/pii-masking-200k",
      "pii_types": []
    },
    {
      "text": "Pr\u00e9paration du laboratoire technologique pour les \u00e9l\u00e8ves de 81. Nous aurons besoin de transf\u00e9rer des fonds du compte 00577440 pour couvrir les d\u00e9penses. Veuillez confirmer au plus t\u00f4t.",
      "expected": "NONE",
      "source": "Isotonic/pii-masking-200k",
      "pii_types": []
    },
    {
      "text": "Il 1913-05-08T07:04:07.947Z, \u00e8 stato effettuato l'accesso su 'Progress Spectrum Beacon' dall'indirizzo Ethereum 0x9743cd7a5dbdf7fa1b4957f4987c80f3c1a5a9ba legato all'account 73961655. Si prega di confermare.",
      "expected": "CUSTOMER_DATA",
      "source": "Isotonic/pii-masking-200k",
      "pii_types": [
        "ADDRESS"
      ]
    },
    {
      "text": "Si prega di pagare Rp per la vaccinazione con la carta di credito 7673190548578600 emessa da american_express.",
      "expected": "NONE",
      "source": "Isotonic/pii-masking-200k",
      "pii_types": []
    },
    {
      "text": "Ti diamo il benvenuto nel nostro programma di benessere su https://jumpy-surroundings.org, accedi con Mozilla/5.0 (Macintosh; PPC Mac OS X 10.7.8; rv:11.7) Gecko/20100101 Firefox/11.7.8.",
      "expected": "CUSTOMER_DATA",
      "source": "Isotonic/pii-masking-200k",
      "pii_types": [
        "URL"
      ]
    },
    {
      "text": "Eine 20 years old-j\u00e4hrige Intersex woman-Patientin berichtete von einer signifikanten Verbesserung der t\u00e4glichen Routinen nach Physiotherapie.",
      "expected": "NONE",
      "source": "Isotonic/pii-masking-200k",
      "pii_types": []
    },
    {
      "text": "Dear participant, we're running a Social psychology experiment testing whether location perceived through IP addresses 24.88.7.161,1f5d:df52:febe:eafa:0ecb:27b3:3913:81c3 can bias people's social interactions online. All data is de-identified. Give us a go!",
      "expected": "NONE",
      "source": "Isotonic/pii-masking-200k",
      "pii_types": []
    },
    {
      "text": "Come azienda globale, supportiamo molte valute per la comodit\u00e0 dei nostri stagisti internazionali. I pagamenti delle tasse possono essere effettuati in Baht (Cedi) o Metical (Lari).",
      "expected": "CUSTOMER_DATA",
      "source": "Isotonic/pii-masking-200k",
      "pii_types": [
        "NAME"
      ]
    },
    {
      "text": "9 years, Female oder Cisgender woman spielt keine Rolle, wenn es darum geht, die Kunst des Zeitmanagements zu beherrschen. Der Schl\u00fcssel ist, Ihre Aufgaben nach Priorit\u00e4t zu sortieren und realistische Ziele zu setzen. Lassen Sie unwichtige Aufgaben nicht Ihre wertvolle Zeit beanspruchen.",
      "expected": "NONE",
      "source": "Isotonic/pii-masking-200k",
      "pii_types": []
    },
    {
      "text": "Bitte \u00fcberweisen Sie \u0440\u0443\u0431Naira auf 4840622526568557 f\u00fcr die morgige kognitive Therapiesitzung.",
      "expected": "NONE",
      "source": "Isotonic/pii-masking-200k",
      "pii_types": []
    },
    {
      "text": "Vaccination time for children with a height of 4' 5\" is between 22 and 18. Please carry your mask and sanitizer.",
      "expected": "NONE",
      "source": "Isotonic/pii-masking-200k",
      "pii_types": []
    },
    {
      "text": "Gabrielle, qu'en pensez-vous de la r\u00e9partition des employ\u00e9s en fonction de leur exp\u00e9rience de projet plut\u00f4t que de la loyaut\u00e9 envers le d\u00e9partement dans Est de l'Angleterre?",
      "expected": "CUSTOMER_DATA",
      "source": "Isotonic/pii-masking-200k",
      "pii_types": [
        "NAME"
      ]
    },
    {
      "text": "Ciao, mi chiamo Dr. e sono uno studente interessato al vostro programma di tirocinio estivo come Agent. Potete fornirmi ulteriori dettagli?",
      "expected": "NONE",
      "source": "Isotonic/pii-masking-200k",
      "pii_types": []
    },
    {
      "text": "Riguardo al report 54476. L'altezza dell'apparecchio a raggi X \u00e8 salita a 5'11\". Potrebbe trattarsi di un errore di calibrazione o di un'indicazione di malfunzionamento. Il suo indirizzo IP \u00e8 168.180.75.120. Potresti controllare questo?",
      "expected": "NONE",
      "source": "Isotonic/pii-masking-200k",
      "pii_types": []
    },
    {
      "text": "We're organized a meeting with education officers in Missouri City. Brief them on IP a5da:ff0b:fd4b:a506:db09:df6d:43b2:a9f2 with password AI2WGh_RxJuu.",
      "expected": "CREDENTIALS",
      "source": "Isotonic/pii-masking-200k",
      "pii_types": [
        "PASSWORD"
      ]
    },
    {
      "text": "Hai bisogno di una consultazione ortopedica per un paziente di 6 anni. Il refertista \u00e8 51.53.73.4. L'altezza del paziente \u00e8 di 0.96m e l'ID del paziente \u00e8 9122746955313555.",
      "expected": "NONE",
      "source": "Isotonic/pii-masking-200k",
      "pii_types": []
    },
    {
      "text": "Your school transport vehicle UGZLFRDUKDTJ69990, QD78YUX will be arriving at location with coordinates [-41.2315,-133.7389] to pick up students as per the new route of Arizona.",
      "expected": "NONE",
      "source": "Isotonic/pii-masking-200k",
      "pii_types": []
    },
    {
      "text": "Notre \u00e9quipe de professionnels du secteur Assurance veille \u00e0 ce que chacun dispose d'une voie num\u00e9rique pour b\u00e9n\u00e9ficier de soins palliatifs. Connectez-vous avec nous via 79da:fb9d:2c9f:fece:d1e3:f5fa:2eb3:af64.",
      "expected": "NONE",
      "source": "Isotonic/pii-masking-200k",
      "pii_types": []
    },
    {
      "text": "Hello, the analytics team needs the data logs of Mozilla/5.0 (compatible; MSIE 9.0; Windows NT 5.2; Trident/7.0; .NET CLR 3.8.78900.2) urgently, especially from 0ca5:ad9b:a9fa:a86f:ef8e:635b:9f26:a3bd address. Contact through main office at 28244 Main Street S",
      "expected": "NONE",
      "source": "Isotonic/pii-masking-200k",
      "pii_types": []
    },
    {
      "text": "Die Pflegepraxis in West Midlands hat die Verwendung hochmoderner Technologie implementiert. Als Teil davon m\u00fcssen alle Mitarbeiter eine g\u00fcltige 26.241.116.94-Adresse f\u00fcr ihre Systeme haben.",
      "expected": "NONE",
      "source": "Isotonic/pii-masking-200k",
      "pii_types": []
    },
    {
      "text": "[@USERNAME_1], die von Ihnen geteilte IP 52ec:7de6:b634:95ad:1ccd:b77c:fc9d:23fb enth\u00e4lt keine aktuellen Daten f\u00fcr das Operations Curriculum. Bitte teilen Sie eine andere.",
      "expected": "NONE",
      "source": "Isotonic/pii-masking-200k",
      "pii_types": []
    },
    {
      "text": "Hallo, Ihre Anmeldung f\u00fcr das Stressbew\u00e4ltigungsseminar f\u00fcr Coordinator am 4/25 war erfolgreich. Denken Sie daran: PIN 6375. F\u00fcr Hilfe w\u00e4hlen Sie (309) 5326841.",
      "expected": "CUSTOMER_DATA",
      "source": "Isotonic/pii-masking-200k",
      "pii_types": [
        "PHONE",
        "DATE"
      ]
    },
    {
      "text": "Hier ist das neue Preismodell, \u00fcber das wir gesprochen haben, Kaley. Denken Sie daran, den Preis f\u00fcr den Bereich Configuration festzulegen und einen Rabatt von 100924 K\u010d f\u00fcr Benutzer von Investment Account anzuwenden. Rufen Sie mich unter +523-657.965-5653 an, wenn Sie Probleme haben.",
      "expected": "CUSTOMER_DATA",
      "source": "Isotonic/pii-masking-200k",
      "pii_types": [
        "PHONE",
        "NAME"
      ]
    },
    {
      "text": "Un piccolo focolaio di una malattia infettiva \u00e8 stato rintracciato a Suite 515, supportato dalla nostra analisi dei pacchetti di dati dall'indirizzo MAC 16:e9:c0:aa:2f:32.",
      "expected": "CUSTOMER_DATA",
      "source": "Isotonic/pii-masking-200k",
      "pii_types": [
        "ADDRESS"
      ]
    },
    {
      "text": "Nous avons h\u00e2te de vous voir \u00e9voluer dans notre environnement Group. Votre poste de travail se trouve \u00e0 Southeast de l'entr\u00e9e, et votre mot de passe de connexion est hq9vWdAiIy7s.",
      "expected": "CREDENTIALS",
      "source": "Isotonic/pii-masking-200k",
      "pii_types": [
        "PASSWORD"
      ]
    },
    {
      "text": "Confermiamo che tu, Rylee, hai partecipato al webinar sul tutoraggio tenutosi il May 13, 1996. Apprezziamo il tuo feedback.",
      "expected": "CUSTOMER_DATA",
      "source": "Isotonic/pii-masking-200k",
      "pii_types": [
        "DATE",
        "NAME"
      ]
    },
    {
      "text": "Unser Jobstandort, der sich in Berlin befindet, s\u00fcdlich von Southwest, hat kontinuierliche Sicherheitsprobleme. Dies erfordert dringende Ma\u00dfnahmen von der Gesch\u00e4ftsleitung.",
      "expected": "NONE",
      "source": "Isotonic/pii-masking-200k",
      "pii_types": []
    },
    {
      "text": "Hallo Transexual male, es ist Zeit f\u00fcr Ihre Impfung. Bitte leisten Sie die Zahlung \u00fcber Ethereum. Anbei finden Sie die Zahlungsadresse: 0x54bcf909cb90ca036979ab07f5efcaabdba638ee.",
      "expected": "CUSTOMER_DATA",
      "source": "Isotonic/pii-masking-200k",
      "pii_types": [
        "ADDRESS"
      ]
    },
    {
      "text": "Die Theoriesitzungen im 61021 n\u00e4chste Woche werden das Lernen auf einzigartige Weise f\u00f6rdern. Stellen Sie sicher, dass Sie Ihre Anmeldeinformationen aktualisieren. Das Passwort GpTGhafg6F9n muss alle 90 Tage aktualisiert werden. Bei Problemen wenden Sie sich bitte an das technische Team unter Angabe der Fahrzeug-VIN: AA9S683YYJS311545.",
      "expected": "CREDENTIALS",
      "source": "Isotonic/pii-masking-200k",
      "pii_types": [
        "PASSWORD"
      ]
    },
    {
      "text": "Kaya, f\u00e9licitations pour votre admission \u00e0 notre programme d'\u00c9ducation Mondiale. Votre LG9xTNZv2r2i6uod43tUfHdsUCZYSCrV t\u00e9moigne de votre engagement envers cette initiative.",
      "expected": "CUSTOMER_DATA",
      "source": "Isotonic/pii-masking-200k",
      "pii_types": [
        "ADDRESS",
        "NAME"
      ]
    },
    {
      "text": "I nostri materiali didattici sono personalizzati in base al tuo profilo educativo, includendo l'et\u00e0 28 years old. Si prega di aggiornare i dettagli rilevanti nel tuo profilo studente Personal Loan Account.",
      "expected": "CUSTOMER_DATA",
      "source": "Isotonic/pii-masking-200k",
      "pii_types": [
        "NAME"
      ]
    },
    {
      "text": "Ben\u00f6tigen Echtzeitdaten zur Ern\u00e4hrungsaufnahme der Sch\u00fcler f\u00fcr ein Projekt, das bald abgeschlossen wird. Bitte geben Sie Jerad58 und MHxJ3rDzooxe ein. Link hierf\u00fcr - https://near-memory.biz/.",
      "expected": "CREDENTIALS",
      "source": "Isotonic/pii-masking-200k",
      "pii_types": [
        "USERNAME",
        "PASSWORD",
        "NAME",
        "URL"
      ]
    },
    {
      "text": "Beschleunigen Sie Ihre Karriere in den MINT-F\u00e4chern mit einem Coding Bootcamp in Palatine. Melden Sie sich noch heute mit IPv6: 857b:aa40:7b1e:349e:7f28:efae:b5b8:fbf4 an!",
      "expected": "NONE",
      "source": "Isotonic/pii-masking-200k",
      "pii_types": []
    },
    {
      "text": "J'ai essay\u00e9 d'ex\u00e9cuter des diagnostics Web pour le client Personal Loan Account, mais j'ai re\u00e7u une erreur concernant la cl\u00e9 publique 1L9j9EeEVJQZBxtsbuxZ2XoYd5mB89GsC89u5. Peut-\u00eatre un probl\u00e8me avec l'int\u00e9gration de paiement ?",
      "expected": "CUSTOMER_DATA",
      "source": "Isotonic/pii-masking-200k",
      "pii_types": [
        "ADDRESS",
        "NAME"
      ]
    },
    {
      "text": "Sei cordialmente invitato a partecipare al nostro seminario internazionale sulle Malattie Infettive. Combattiamo insieme. Per ulteriori dettagli, contatta Dakota, il Customer Communications Technician.",
      "expected": "CUSTOMER_DATA",
      "source": "Isotonic/pii-masking-200k",
      "pii_types": [
        "NAME"
      ]
    },
    {
      "text": "Cher Abraham, voici votre num\u00e9ro de compte \u00e9tudiant unique 58444993. Cela sera n\u00e9cessaire pour toutes vos transactions pendant votre programme d'\u00e9change \u00e9tudiant.",
      "expected": "CUSTOMER_DATA",
      "source": "Isotonic/pii-masking-200k",
      "pii_types": [
        "NAME"
      ]
    },
    {
      "text": "Cher Sydnie, votre analyse d\u00e9taill\u00e9e des tendances en mati\u00e8re de sant\u00e9 \u00e0 partir de [-59.1818,-53.903] a \u00e9t\u00e9 instructive. Nous avons remarqu\u00e9 des sch\u00e9mas similaires dans notre ensemble de donn\u00e9es \u00e9galement.",
      "expected": "CUSTOMER_DATA",
      "source": "Isotonic/pii-masking-200k",
      "pii_types": [
        "NAME"
      ]
    },
    {
      "text": "Suite \u00e0 votre int\u00e9r\u00eat pour les tests g\u00e9n\u00e9tiques, nous avons fix\u00e9 un rendez-vous pour vous. Veuillez participer avec le montant exact de \u20ba426,416.86.",
      "expected": "NONE",
      "source": "Isotonic/pii-masking-200k",
      "pii_types": []
    },
    {
      "text": "A volunteer's parent's credit card details, 4045170458194145 (discover), was accidentally submitted. Remove this data immediately and please notify them at 111.197.8.71 via user agent Opera/13.21 (X11; Linux x86_64; U; KO Presto/2.9.161 Version/11.00). Confirm completion with coded SMS 0074349771369050.",
      "expected": "NONE",
      "source": "Isotonic/pii-masking-200k",
      "pii_types": []
    },
    {
      "text": "Sehr geehrter Madelynn, wir haben Vorw\u00fcrfe wegen \u00e4rztlichen Kunstfehlers von einem 36 years Patienten 4985172028159514 erhalten. Bitte \u00fcberpr\u00fcfen Sie Auto Loan Account so bald wie m\u00f6glich.",
      "expected": "CUSTOMER_DATA",
      "source": "Isotonic/pii-masking-200k",
      "pii_types": [
        "NAME"
      ]
    },
    {
      "text": "Liebes Team, es wurde mehrfach versucht, 8f9waKdcGC2_, das mit Marge24@yahoo.com verbunden ist, von 214.67.205.119 zu \u00e4ndern. Bitte untersuchen Sie dies.",
      "expected": "CREDENTIALS",
      "source": "Isotonic/pii-masking-200k",
      "pii_types": [
        "PASSWORD",
        "EMAIL"
      ]
    },
    {
      "text": "Dies ist Antonina Logan Lowe, ein aktueller Student der XYZ Universit\u00e4t. Ich bin an Ihrem Sommerpraktikumsprogramm interessiert. Sie k\u00f6nnen mich unter +899.05-137-3295 oder Wilton_Metz67@hotmail.com erreichen.",
      "expected": "CUSTOMER_DATA",
      "source": "Isotonic/pii-masking-200k",
      "pii_types": [
        "PHONE",
        "NAME",
        "EMAIL"
      ]
    },
    {
      "text": "Willkommen in unserer Therapieeinrichtung, Cisgender woman. Unsere Priorit\u00e4t liegt darin, eine effektive Therapie anzubieten und Ihre Daten wie 4798862441283049, Apt. 929, 83082, Maximo Underpass, Neuenburg, 50547 zu sch\u00fctzen.",
      "expected": "CUSTOMER_DATA",
      "source": "Isotonic/pii-masking-200k",
      "pii_types": [
        "ADDRESS"
      ]
    },
    {
      "text": "Liebe Geovany, Ihre Bewerbung f\u00fcr das Austauschprogramm wurde erhalten. Bitte t\u00e4tigen Sie die Zahlung mit dem Konto 68252188 bei der ZXUFKY3NQ39 Bank, um Ihren Platz zu sichern.",
      "expected": "CUSTOMER_DATA",
      "source": "Isotonic/pii-masking-200k",
      "pii_types": [
        "NAME"
      ]
    },
    {
      "text": "Jeder Raum in 43178 Beech Close ist jetzt mit IP-Kameras f\u00fcr zus\u00e4tzliche Sicherheit ausgestattet. Bitte respektieren Sie die Privatsph\u00e4re aller und seien Sie vorsichtig.",
      "expected": "NONE",
      "source": "Isotonic/pii-masking-200k",
      "pii_types": []
    },
    {
      "text": "Als Wissenschaftler des Jahres sind Sie berechtigt, an der Bewertung der Lehrerleistung teilzunehmen. Bitte rufen Sie 03877-157023 an. Hinweis: Dieser Anruf erfordert eine Authentifizierung. Ihr Geheimcode lautet 7373.",
      "expected": "CUSTOMER_DATA",
      "source": "Isotonic/pii-masking-200k",
      "pii_types": [
        "PHONE"
      ]
    },
    {
      "text": "Hallo Herr Runte-Heathcote, Basierend auf den k\u00fcrzlichen Diskussionen \u00fcber die Schuluniformrichtlinie m\u00f6chten wir gerne Ihre Perspektive h\u00f6ren, basierend auf Ihrer Rolle als Direct Applications Facilitator. Bitte teilen Sie Ihre Einsichten vor dem 7th April mit. Vielen Dank!",
      "expected": "CUSTOMER_DATA",
      "source": "Isotonic/pii-masking-200k",
      "pii_types": [
        "DATE",
        "NAME"
      ]
    },
    {
      "text": "Il paziente Bigender codificato come 06958-7354 ha subito un'operazione di successo.",
      "expected": "NONE",
      "source": "Isotonic/pii-masking-200k",
      "pii_types": []
    },
    {
      "text": "Cas d'urgence : MTF, 23 years old, emplacement - [-86.2217,-69.2081]. Ant\u00e9c\u00e9dents m\u00e9dicaux - incidents cardiovasculaires mineurs. Envoyez une ambulance \u00e0 Bramley Close 9224, Northamptonshire. Priorit\u00e9 !",
      "expected": "NONE",
      "source": "Isotonic/pii-masking-200k",
      "pii_types": []
    },
    {
      "text": "Notizie entusiasmanti per tutti i dipendenti di Stracke - Sipes! Abbiamo spostato il nostro programma di benessere online. Puoi accedere al portale su https://present-problem.name/. Il tuo nome utente \u00e8 Marianna_Bechtelar2 con password a9WDA18MSP4q.",
      "expected": "CREDENTIALS",
      "source": "Isotonic/pii-masking-200k",
      "pii_types": [
        "USERNAME",
        "PASSWORD",
        "NAME",
        "URL"
      ]
    },
    {
      "text": "Mireille, beachten Sie das angeh\u00e4ngte Dokument in der E-Mail Tania.Smitham@gmail.com, die Sie f\u00fcr einen speziell auf Ihre Bed\u00fcrfnisse zugeschnittenen Di\u00e4tplan bereitgestellt haben, unter Ber\u00fccksichtigung der Daten 202 33 5058. Bitte nehmen Sie dies zur fr\u00fchestm\u00f6glichen Beratung in Anspruch.",
      "expected": "CUSTOMER_DATA",
      "source": "Isotonic/pii-masking-200k",
      "pii_types": [
        "SSN",
        "NAME",
        "EMAIL"
      ]
    },
    {
      "text": "Avviso: Come paziente, avete il diritto alla privacy. La salvaguardia dei vostri dati personali, inclusi il vostro 3ydET8rBkaXGbnqYjRWh1ni7ASCTUJspJEvcUYgF e 0xf768eb498bbaacc98ba69e5fb17021a5fadca27b, \u00e8 responsabilit\u00e0 nostra.",
      "expected": "CUSTOMER_DATA",
      "source": "Isotonic/pii-masking-200k",
      "pii_types": [
        "ADDRESS"
      ]
    },
    {
      "text": "Nach dem letzten Cybersecurity-Breaches bei Bashirian - Schimmel sind alle Mitarbeiter, die Zugriff auf sensible Daten haben, verpflichtet, ihre Fahrzeug-VIN-Nummer E9H28A10HXP562429 zur \u00dcberpr\u00fcfung zusammen mit anderen pers\u00f6nlichen Daten anzugeben.",
      "expected": "CUSTOMER_DATA",
      "source": "Isotonic/pii-masking-200k",
      "pii_types": [
        "NAME"
      ]
    },
    {
      "text": "Bonjour Amira, Nous avons mis \u00e0 jour votre adresse MMAWcZmSWrog1y6HqYCjwxx81CmMVuU enregistr\u00e9e pour les paiements des consultations p\u00e9diatriques de votre enfant.",
      "expected": "CUSTOMER_DATA",
      "source": "Isotonic/pii-masking-200k",
      "pii_types": [
        "ADDRESS",
        "NAME"
      ]
    },
    {
      "text": "La collecte de donn\u00e9es pour l'\u00e9tude de la couleur des yeux Brown a \u00e9t\u00e9 archiv\u00e9e sous l'identifiant 61-995790-780640-4. Les donn\u00e9es sensibles incluent le 75641456892 et la 6/26 des sujets.",
      "expected": "CUSTOMER_DATA",
      "source": "Isotonic/pii-masking-200k",
      "pii_types": [
        "PHONE",
        "SSN"
      ]
    },
    {
      "text": "There were some errors during our legal tech data migration. Log in at https://enraged-grandmother.biz with password CJmFWsSu_A_b for details.",
      "expected": "CREDENTIALS",
      "source": "Isotonic/pii-masking-200k",
      "pii_types": [
        "PASSWORD",
        "URL"
      ]
    },
    {
      "text": "Les dispositifs portables, imagin\u00e9s comme un simple JSW30BFG4GYN53039, peuvent suivre les signes vitaux de sant\u00e9 en temps r\u00e9el, transmettant des donn\u00e9es via des adresses IP sp\u00e9cifiques ou 9f:13:e1:6c:0f:f1. L'informatique de la sant\u00e9 exploite cette technologie pour g\u00e9rer efficacement les dossiers des patients.",
      "expected": "NONE",
      "source": "Isotonic/pii-masking-200k",
      "pii_types": []
    },
    {
      "text": "Il webinar 'Innovazioni nella medicina dello sport' \u00e8 programmato per il July 23, 1958. Se vivi a Southwest, potresti essere idoneo a uno sconto.",
      "expected": "NONE",
      "source": "Isotonic/pii-masking-200k",
      "pii_types": []
    },
    {
      "text": "Das w\u00f6chentliche Treffen findet am n\u00e4chsten Montag statt. Wir verwenden Mozilla/5.0 (Windows; U; Windows NT 5.1)AppleWebKit/538.2.2 (KHTML, like Gecko) Version/6.0.7 Safari/538.2.2 zur Verbindung. Falls es nicht installiert ist, verwenden Sie die Anmeldedaten: Bonita_OHara und das Passwort 6n_ZYwt2tR1_.",
      "expected": "CREDENTIALS",
      "source": "Isotonic/pii-masking-200k",
      "pii_types": [
        "USERNAME",
        "PASSWORD",
        "NAME"
      ]
    },
    {
      "text": "Nous avons re\u00e7u vos rapports m\u00e9dicaux et les avons \u00e9valu\u00e9s en cons\u00e9quence. Notre Legacy Functionality Representative a not\u00e9 les sp\u00e9cificit\u00e9s concernant la couleur de vos yeux, qui est Eye color: Green. Nous entreprendrons des traitements de pr\u00e9cision en tenant compte de cela.",
      "expected": "NONE",
      "source": "Isotonic/pii-masking-200k",
      "pii_types": []
    },
    {
      "text": "Following your interest in Genetic Testing, we've set an appointment for you. Please chip in with the exact amount of \u17db387437.",
      "expected": "NONE",
      "source": "Isotonic/pii-masking-200k",
      "pii_types": []
    },
    {
      "text": "Ciao, il saldo del tuo account in Kwanza sembra insufficiente per la transazione. Puoi aggiornare i tuoi dati tramite il link con G9pi3dbMU0SY.",
      "expected": "CREDENTIALS",
      "source": "Isotonic/pii-masking-200k",
      "pii_types": [
        "PASSWORD"
      ]
    },
    {
      "text": "Gem\u00e4\u00df den neuesten Richtlinien ist Man der Ansprechpartner. Bitte senden Sie die rechtlichen Dokumente an Apt. 327. F\u00fcgen Sie zur Best\u00e4tigung der Transaktion MoCX57wvvnNmCxr7g7b3is4G7tV8Q6G4 bei.",
      "expected": "CUSTOMER_DATA",
      "source": "Isotonic/pii-masking-200k",
      "pii_types": [
        "ADDRESS"
      ]
    },
    {
      "text": "Pour d\u00e9bloquer plus de fonctionnalit\u00e9s, fournissez des informations de paiement telles que discover 5953581144008308 et 421.",
      "expected": "NONE",
      "source": "Isotonic/pii-masking-200k",
      "pii_types": []
    },
    {
      "text": "Lesen Sie einen Artikel, ver\u00f6ffentlicht von Facilitator, \u00fcber die Rechte von privaten Schulen in [58.9361,57.5625]. K\u00f6nnten Sie mir eine gegenteilige Meinung dazu nennen?",
      "expected": "NONE",
      "source": "Isotonic/pii-masking-200k",
      "pii_types": []
    },
    {
      "text": "Ciao Lamar, abbiamo ricevuto un finanziamento di 0.5844m Yen da parte del Lindgren - Powlowski per il nostro nuovo dispositivo medico. I dettagli della transazione sono nel tuo Oleta36@hotmail.com.",
      "expected": "CUSTOMER_DATA",
      "source": "Isotonic/pii-masking-200k",
      "pii_types": [
        "NAME",
        "EMAIL"
      ]
    },
    {
      "text": "Chers parents, nous sommes honor\u00e9s d'avoir Beulah Hayes-Wunsch en tant que nouveau Lead Integration Producer pour le d\u00e9partement de l'\u00e9ducation sp\u00e9cialis\u00e9e.",
      "expected": "CUSTOMER_DATA",
      "source": "Isotonic/pii-masking-200k",
      "pii_types": [
        "NAME"
      ]
    },
    {
      "text": "Les audits de certification de l'assurance qualit\u00e9 pour le site 20231 de votre entreprise sont pr\u00e9vus pour le December 17, 1919. Si cela vous convient, confirmez par \u00e9crit \u00e0 Dannie Runolfsson \u00e0 l'adresse Vesta_Torp18@yahoo.com.",
      "expected": "CUSTOMER_DATA",
      "source": "Isotonic/pii-masking-200k",
      "pii_types": [
        "DATE",
        "NAME",
        "EMAIL"
      ]
    },
    {
      "text": "Ho ricevuto una mail dal paziente 51163 riguardo al suo interesse per un nuovo piano dietetico. Ha chiesto informazioni sui costi, pagati tramite 6305485464262123. Ha detto di volerlo provare nel lungo termine per gestire la sua malattia.",
      "expected": "NONE",
      "source": "Isotonic/pii-masking-200k",
      "pii_types": []
    },
    {
      "text": "Commenc\u00e9e en 15/01/1912, la m\u00e9decine pr\u00e9ventive joue un r\u00f4le vital dans la sant\u00e9 ult\u00e9rieure de ceux qui entrent dans leur 36 years cette ann\u00e9e.",
      "expected": "NONE",
      "source": "Isotonic/pii-masking-200k",
      "pii_types": []
    },
    {
      "text": "Stiamo pianificando di condurre un workshop presso 898 sull'aggiornamento del curriculum per Solutions. Coinvolgiamo Thaddeus Treutel per questo.",
      "expected": "CUSTOMER_DATA",
      "source": "Isotonic/pii-masking-200k",
      "pii_types": [
        "NAME"
      ]
    },
    {
      "text": "Il programma di benessere si concentra anche sulla salute fisica, con il nuovo studio di yoga che sar\u00e0 allestito presso il 719 Suite 393.",
      "expected": "CUSTOMER_DATA",
      "source": "Isotonic/pii-masking-200k",
      "pii_types": [
        "ADDRESS"
      ]
    },
    {
      "text": "L'appuntamento di follow-up per Mr. Alexis Parker Wisozk, genere Intersex man, \u00e8 stato programmato per il 16/02/2014 alle 18:40. Le sue principali preoccupazioni includono un aumento del numero di imperfezioni e una pelle persistentemente secca.",
      "expected": "CUSTOMER_DATA",
      "source": "Isotonic/pii-masking-200k",
      "pii_types": [
        "DATE",
        "NAME"
      ]
    },
    {
      "text": "Ce semestre, notre programme met l'accent sur une compr\u00e9hension plus approfondie des changements physiques et \u00e9motionnels pendant l'adolescence pour les Male et Male.",
      "expected": "NONE",
      "source": "Isotonic/pii-masking-200k",
      "pii_types": []
    },
    {
      "text": "Das Englisch-Arbeitsblatt ist auf https://evergreen-fraud.biz verf\u00fcgbar. Das Anmeldepasswort lautet CAafoIMnVmzJ. Bei technischen Problemen wenden Sie sich bitte an 200.148.69.188.",
      "expected": "CREDENTIALS",
      "source": "Isotonic/pii-masking-200k",
      "pii_types": [
        "PASSWORD",
        "URL"
      ]
    },
    {
      "text": "Cher 02/08/1941, mon enfant a d\u00fb partir plus t\u00f4t le 10/89 en raison d'une urgence personnelle. Veuillez excuser son absence, Cordialement, Apt. 198.",
      "expected": "CUSTOMER_DATA",
      "source": "Isotonic/pii-masking-200k",
      "pii_types": [
        "DATE",
        "ADDRESS"
      ]
    },
    {
      "text": "The last set of images for the patient with Grey eyes seem a little off. Can you cross-check them on machine with MAC address 29:51:78:a4:fb:52?",
      "expected": "NONE",
      "source": "Isotonic/pii-masking-200k",
      "pii_types": []
    },
    {
      "text": "Salut Yvette, laissez-moi vous pr\u00e9senter Dell Sage Homenick, notre nouveau Customer Communications Orchestrator Accountability dans notre entreprise.",
      "expected": "CUSTOMER_DATA",
      "source": "Isotonic/pii-masking-200k",
      "pii_types": [
        "NAME"
      ]
    },
    {
      "text": "La semaine d'\u00e9ducation en plein air est pr\u00e9vue. Les \u00e9tudiants de Oxfordshire sont les bienvenus. Communiquez via 62.211.138.39. Itin\u00e9raire : Southeast. Les paiements peuvent \u00eatre effectu\u00e9s avec 7096481819833482 avec le CVV 793 et l'\u00e9metteur de carte american_express.",
      "expected": "NONE",
      "source": "Isotonic/pii-masking-200k",
      "pii_types": []
    },
    {
      "text": "I'd like to invest in your start-up. I'll be transferring funds from my account, 44911291. The kr967985 will arrive within 2 business days.",
      "expected": "NONE",
      "source": "Isotonic/pii-masking-200k",
      "pii_types": []
    },
    {
      "text": "Die Anmeldedaten f\u00fcr den medizinischen Bildgebungsprozess lauten wie folgt: URL - https://monstrous-thunderhead.org, Benutzername - Mozilla/5.0 (X11; Linux i686 AppleWebKit/534.2.2 (KHTML, like Gecko) Chrome/26.0.877.0 Safari/534.2.2, Passwort - OQEj0LdAwVUd.",
      "expected": "CREDENTIALS",
      "source": "Isotonic/pii-masking-200k",
      "pii_types": [
        "PASSWORD",
        "URL"
      ]
    },
    {
      "text": "Bonjour Jace, ceci est un rappel concernant votre rendez-vous de contr\u00f4le en endocrinologie pr\u00e9vu pour demain. Veuillez confirmer votre pr\u00e9sence en nous envoyant un email \u00e0 Stan.Williamson98@hotmail.com.",
      "expected": "CUSTOMER_DATA",
      "source": "Isotonic/pii-masking-200k",
      "pii_types": [
        "NAME",
        "EMAIL"
      ]
    },
    {
      "text": "Die j\u00e4hrliche Konferenz zur Organisationsentwicklung in Calhoun County wurde in eine andere Postleitzahl verschoben: 40584.",
      "expected": "NONE",
      "source": "Isotonic/pii-masking-200k",
      "pii_types": []
    },
    {
      "text": "Anweisungen f\u00fcr den standardisierten Test: Alle Sch\u00fcler sollten ihren Ausweis, 8974664918094559 zur \u00dcberpr\u00fcfung und kr184k f\u00fcr Bearbeitungsgeb\u00fchren mitbringen.",
      "expected": "NONE",
      "source": "Isotonic/pii-masking-200k",
      "pii_types": []
    },
    {
      "text": "Vielen Dank, Janice.Ernser, dass Sie sich f\u00fcr das Wellness-Programm angemeldet haben. Ihre Geb\u00fchr von 207627.28 Boliviano boliviano wird \u00fcber die Karte mit der Endnummer 6145572627348036 eingezogen.",
      "expected": "CUSTOMER_DATA",
      "source": "Isotonic/pii-masking-200k",
      "pii_types": [
        "USERNAME",
        "NAME"
      ]
    },
    {
      "text": "Le ricette per il paziente Cameron saranno inviate a Kuphal Club, Hampshire.",
      "expected": "CUSTOMER_DATA",
      "source": "Isotonic/pii-masking-200k",
      "pii_types": [
        "NAME"
      ]
    },
    {
      "text": "Per ritirare i materiali artistici, ti preghiamo di guidare il tuo veicolo KC35PRE (VIN BDEVR1MZFGH578565) fino al punto di ritiro presso le coordinate [-19.1024,-5.8879].",
      "expected": "NONE",
      "source": "Isotonic/pii-masking-200k",
      "pii_types": []
    },
    {
      "text": "Ciao Ms., secondo i nostri registri, sei idoneo per un finanziamento educativo questo semestre. Accreditiamo Uganda Shilling706081.82 sulla tua carta di credito 6831127341296116. Assicurati che tutti i tuoi dati siano aggiornati per garantire transazioni senza problemi.",
      "expected": "NONE",
      "source": "Isotonic/pii-masking-200k",
      "pii_types": []
    },
    {
      "text": "Engineer, we have seen a spike in audience interactions from our IPv4 address 84.22.245.158. Could you explore this, and identify possible strategies to leverage this increasing audience engagement?",
      "expected": "NONE",
      "source": "Isotonic/pii-masking-200k",
      "pii_types": []
    },
    {
      "text": "We've recently shipped new pharmaceutical goods to Quebec through Northeast route. Make sure the goods are monitored in-transit via GPS Coordinate: [-42.306,172.4064]. Notify the Admin Specialist in case of delays.",
      "expected": "NONE",
      "source": "Isotonic/pii-masking-200k",
      "pii_types": []
    },
    {
      "text": "Ciao Rocky, abbiamo rilevato tentativi di accesso al tuo account di apprendimento online da questo dispositivo insolito ed:27:fd:a3:ba:b3. Se questo non \u00e8 il tuo dispositivo, ti preghiamo di contattarci e di modificare la tua password. Password attuale: hkt1eyjehhyO",
      "expected": "CREDENTIALS",
      "source": "Isotonic/pii-masking-200k",
      "pii_types": [
        "PASSWORD",
        "NAME"
      ]
    },
    {
      "text": "Ciao Alfonso. Congratulazioni per il tuo voto A. I dettagli sono ora disponibili in Bergnaum Brooks, 2073 nell'angolo degli studenti. Contattami al (195)-3130185 se hai qualche dubbio.",
      "expected": "CUSTOMER_DATA",
      "source": "Isotonic/pii-masking-200k",
      "pii_types": [
        "PHONE",
        "NAME"
      ]
    },
    {
      "text": "Dieser F\u00f6rdergenehmigungsprozess erfordert die \u00dcberpr\u00fcfung Ihrer BIC-Nummer GDHSCAW6XXX. Sobald dies erledigt ist, werden die Gelder in Tunisian Dinar \u00fcberwiesen.",
      "expected": "NONE",
      "source": "Isotonic/pii-masking-200k",
      "pii_types": []
    },
    {
      "text": "Notre initiative en mati\u00e8re de sant\u00e9 vise \u00e0 couvrir chaque recoin de Tessin. Nous atteignons m\u00eame les zones les plus recul\u00e9es. Pour faciliter les d\u00e9placements, nous appr\u00e9cierions vivement des dons tels que des v\u00e9hicules de transport en commun portant la plaque d'immatriculation SX09CSQ.",
      "expected": "NONE",
      "source": "Isotonic/pii-masking-200k",
      "pii_types": []
    },
    {
      "text": "Cher Roselyn, je constate que vous approchez de votre 90e anniversaire 3/09. Une alimentation appropri\u00e9e est maintenant plus cruciale que jamais. Discutons des changements alimentaires \u00e0 mettre en place pour vous maintenir en bonne sant\u00e9.",
      "expected": "CUSTOMER_DATA",
      "source": "Isotonic/pii-masking-200k",
      "pii_types": [
        "NAME"
      ]
    },
    {
      "text": "Il nostro portale online https://antique-race.info/ \u00e8 pronto per il prossimo sondaggio sulla nutrizione scolastica. Per assistenza, chiamare il nostro Group al numero 82-114677-781328-6 o inviarci una email all'indirizzo Cayla31@hotmail.com.",
      "expected": "CUSTOMER_DATA",
      "source": "Isotonic/pii-masking-200k",
      "pii_types": [
        "PHONE",
        "URL",
        "EMAIL"
      ]
    },
    {
      "text": "Die Gesundheits- und Sicherheitspr\u00e4sentation ist f\u00fcr 6 AM geplant. Der Schwerpunkt liegt auf korrekten Hebetechniken f\u00fcr Menschen aller 1.72 m Gr\u00f6\u00dfen. Bitte stellen Sie sicher, dass um Sie herum ausreichend Platz f\u00fcr die Teilnahme an dieser Sitzung ist.",
      "expected": "NONE",
      "source": "Isotonic/pii-masking-200k",
      "pii_types": []
    },
    {
      "text": "Besoin d'une attention imm\u00e9diate: le sp\u00e9cialiste Accounts a signal\u00e9 une menace potentielle pour la s\u00e9curit\u00e9 provenant de l'adresse IP 9.75.65.145. Toutes les donn\u00e9es cliniques doivent \u00eatre v\u00e9rifi\u00e9es.",
      "expected": "NONE",
      "source": "Isotonic/pii-masking-200k",
      "pii_types": []
    },
    {
      "text": "'J'ai besoin de ton aide, Mae. Le projet STEM situ\u00e9 aux coordonn\u00e9es GPS [13.9552,-161.6754] a tir\u00e9 une fus\u00e9e vers la direction Northwest. Peux-tu la r\u00e9cup\u00e9rer?'",
      "expected": "CUSTOMER_DATA",
      "source": "Isotonic/pii-masking-200k",
      "pii_types": [
        "NAME"
      ]
    },
    {
      "text": "Les initiatives STEM dans notre \u00e9cole commencent tr\u00e8s bien ce trimestre. Juste pour rappel, veuillez mettre \u00e0 jour les documents de l'\u00e9quipe et les d\u00e9penses en utilisant le compte suivant 8014843783982009, 345 avant 4/50.",
      "expected": "NONE",
      "source": "Isotonic/pii-masking-200k",
      "pii_types": []
    },
    {
      "text": "Gli studenti che non hanno attivato i loro portali di gestione del tempo possono seguire il manuale utente disponibile online. Si prega di utilizzare il browser Mozilla/5.0 (X11; Linux i686; rv:8.1) Gecko/20100101 Firefox/8.1.6 per ottenere i migliori risultati. Questo sar\u00e0 vantaggioso per tutti gli studenti, indipendentemente dal loro hazel.",
      "expected": "NONE",
      "source": "Isotonic/pii-masking-200k",
      "pii_types": []
    },
    {
      "text": "Der Test wurde von der IPV4-Adresse 50.83.34.103 und der IPV6-Adresse 8a41:adac:2ab5:49ca:acfc:bfec:9f3c:2de0 kompromittiert. Die Untersuchung ist im Gange.",
      "expected": "NONE",
      "source": "Isotonic/pii-masking-200k",
      "pii_types": []
    },
    {
      "text": "Customer Applications Associate F\u00e4higkeiten Workshop: Steigern Sie die Freizeit und reduzieren Sie Stress durch Zeitmanagement. Seminarinformationen verf\u00fcgbar auf Mozilla/5.0 (Macintosh; Intel Mac OS X 10_9_5)  AppleWebKit/536.2.1 (KHTML, like Gecko) Chrome/27.0.826.0 Safari/536.2.1.",
      "expected": "NONE",
      "source": "Isotonic/pii-masking-200k",
      "pii_types": []
    },
    {
      "text": "Un avis important \u00e0 tous les travailleurs de la sant\u00e9 de Christinamouth, le portail d'inscription \u00e0 la vaccination exige d\u00e9sormais une identification via 0xa64698cafb804ed5ee5e9553b6c89ef8dbf1ab2f. Veuillez mettre \u00e0 jour vos informations d'identification d\u00e8s que possible.",
      "expected": "CUSTOMER_DATA",
      "source": "Isotonic/pii-masking-200k",
      "pii_types": [
        "ADDRESS"
      ]
    },
    {
      "text": "F\u00fcr einfachere Transaktionen installieren Sie bitte unsere Bibliotheks-App auf Ihrem Ger\u00e4t. Verwenden Sie bitte Sven.Hartmann und lH7PBPXkG0tU f\u00fcr den Erstlogin.",
      "expected": "CREDENTIALS",
      "source": "Isotonic/pii-masking-200k",
      "pii_types": [
        "USERNAME",
        "PASSWORD",
        "NAME"
      ]
    },
    {
      "text": "Students should always keep personal information confidential to maintain online safety. Personal information includes sensitive data such as 10/87, Gns5ftAilMbx, and every 7307.",
      "expected": "CREDENTIALS",
      "source": "Isotonic/pii-masking-200k",
      "pii_types": [
        "PASSWORD"
      ]
    },
    {
      "text": "Un patient Female a \u00e9t\u00e9 admis avec des sympt\u00f4mes aujourd'hui. Le patient travaille en tant que Officer et r\u00e9side dans le Worcestershire.",
      "expected": "NONE",
      "source": "Isotonic/pii-masking-200k",
      "pii_types": []
    },
    {
      "text": "L'enseignante actuelle pour Infrastructure a montr\u00e9 de grandes am\u00e9liorations depuis sa nomination en tant que Forward Response Developer.",
      "expected": "NONE",
      "source": "Isotonic/pii-masking-200k",
      "pii_types": []
    },
    {
      "text": "Hallo, um Probleme beim Einreichen von Aufs\u00e4tzen zu vermeiden, achten Sie darauf, dass Ihre sekund\u00e4re Adresse Apt. 215 mit der in Ihrem Studentenprofil \u00fcbereinstimmt. Falsche Adressen k\u00f6nnten dazu f\u00fchren, dass Ihr Beitrag disqualifiziert wird. Wenden Sie sich bei Bedarf an den Helpdesk unter 83-736151-040557-9.",
      "expected": "CUSTOMER_DATA",
      "source": "Isotonic/pii-masking-200k",
      "pii_types": [
        "PHONE",
        "ADDRESS"
      ]
    },
    {
      "text": "Gentile Male Quigley, stiamo aspettando i tuoi referti medici, per favore inviali a Kendall.Wyman@yahoo.com e effettua un pagamento di z\u0142 0.000b per l'elaborazione dei documenti.",
      "expected": "CUSTOMER_DATA",
      "source": "Isotonic/pii-masking-200k",
      "pii_types": [
        "NAME",
        "EMAIL"
      ]
    },
    {
      "text": "Gli stock presso il magazzino 28851 in 43714-1013 sembrano inconsistenti. Per favore, rivedi secondo le linee guida di Facilitator.",
      "expected": "NONE",
      "source": "Isotonic/pii-masking-200k",
      "pii_types": []
    },
    {
      "text": "Nous avons mis en place une visite virtuelle de l'institution proche des coordonn\u00e9es GPS [74.2399,157.6494]. Veuillez avoir votre akLNYNvtmRAa pr\u00eat, car la visite n\u00e9cessite une authentification du compte.",
      "expected": "CREDENTIALS",
      "source": "Isotonic/pii-masking-200k",
      "pii_types": [
        "PASSWORD"
      ]
    },
    {
      "text": "Le r\u00e9habilitant Female to male transsexual man commence une nouvelle phase. Pass\u00e9 de Apt. 221 \u00e0 04378. Suivi via 61-943231-431022-6. 1247743768704004 sauvegard\u00e9 pour les paiements.",
      "expected": "CUSTOMER_DATA",
      "source": "Isotonic/pii-masking-200k",
      "pii_types": [
        "PHONE",
        "ADDRESS"
      ]
    },
    {
      "text": "Bonjour, je m'appelle Ms. Arden. Je suis Forward Branding Manager de West Glamorgan. J'aimerais demander des informations suppl\u00e9mentaires sur votre s\u00e9rie de trigonom\u00e9trie. Contactez-moi via 62424035.",
      "expected": "CUSTOMER_DATA",
      "source": "Isotonic/pii-masking-200k",
      "pii_types": [
        "NAME"
      ]
    },
    {
      "text": "All vaccination workers are required to watch the latest video on vaccination procedure. To access the video, enter the password T0T40DJlV_ot. Please cover this material before 19/08/1973.",
      "expected": "CREDENTIALS",
      "source": "Isotonic/pii-masking-200k",
      "pii_types": [
        "PASSWORD",
        "DATE"
      ]
    },
    {
      "text": "Florencio, la tua password per la piattaforma di Apprendimento a Distanza \u00e8: RTYdOcnhKFaN. Effettua l'accesso tramite 133.84.250.241 alle 10:07 PM.",
      "expected": "CREDENTIALS",
      "source": "Isotonic/pii-masking-200k",
      "pii_types": [
        "PASSWORD",
        "NAME"
      ]
    },
    {
      "text": "Unsere medizinische Einrichtung in 14059 wurde am 12th October er\u00f6ffnet. Ich ben\u00f6tige die Daten von Male Patienten, die seit diesem Datum geboren wurden, f\u00fcr eine Studie.",
      "expected": "NONE",
      "source": "Isotonic/pii-masking-200k",
      "pii_types": []
    },
    {
      "text": "Caro Phoenix, aggiornamento proveniente da 2770. Il tasso di alfabetizzazione \u00e8 in aumento! Si sono recentemente trasferiti a 87609, Nunavut. Aggiorna il nostro database sul server 71ef:d305:626e:cca8:471c:67dc:0d9b:cfa7, la PASSWORD \u00e8 OaHsunYvkZ4U.",
      "expected": "CREDENTIALS",
      "source": "Isotonic/pii-masking-200k",
      "pii_types": [
        "PASSWORD",
        "NAME"
      ]
    },
    {
      "text": "The game starts at 21:45. Catch a bus from Main Street N, West Midlands and don't forget to get your jerseys of 193cm. See you on the field!",
      "expected": "NONE",
      "source": "Isotonic/pii-masking-200k",
      "pii_types": []
    },
    {
      "text": "Remarquez une l\u00e9g\u00e8re diff\u00e9rence dans les quantit\u00e9s au lieu 343. Administrator peut-il r\u00e9soudre cela?",
      "expected": "NONE",
      "source": "Isotonic/pii-masking-200k",
      "pii_types": []
    },
    {
      "text": "Habe einen Grundst\u00fccksstreit bei 1829 Marcella Lakes. Gibt es rechtliche Ratschl\u00e4ge f\u00fcr eine M2F?",
      "expected": "NONE",
      "source": "Isotonic/pii-masking-200k",
      "pii_types": []
    },
    {
      "text": "Per professionisti come Mr. in una posizione Planner, trovare un equilibrio tra le richieste professionali e la vita personale pu\u00f2 portare a uno stress e un'ansia significativi.",
      "expected": "NONE",
      "source": "Isotonic/pii-masking-200k",
      "pii_types": []
    },
    {
      "text": "Nel meeting virtuale di domani, Silas di Roob - MacGyver parler\u00e0 del suo viaggio di 59 anni come Female in SEL. Accedi tramite bd6e:45d5:7f14:47a6:ae53:9ecd:40e9:3ffb.",
      "expected": "CUSTOMER_DATA",
      "source": "Isotonic/pii-masking-200k",
      "pii_types": [
        "NAME"
      ]
    },
    {
      "text": "Cher(e) Mr., notre \u00e9quipe vous encourage \u00e0 participer \u00e0 la Quality, cela peut vous aider \u00e0 d\u00e9velopper des traits b\u00e9n\u00e9fiques pour vos \u00e9tudes.",
      "expected": "NONE",
      "source": "Isotonic/pii-masking-200k",
      "pii_types": []
    },
    {
      "text": "Ciao Lyla, le tue credenziali di accesso sono: Nome utente - Home Loan Account e password docPBaVuYWrk per partecipare al corso di apprendimento a distanza.",
      "expected": "CREDENTIALS",
      "source": "Isotonic/pii-masking-200k",
      "pii_types": [
        "PASSWORD",
        "NAME"
      ]
    },
    {
      "text": "Wir suchen einen Associate f\u00fcr unsere bevorstehende klinische Studie, die den Einsatz des experimentellen Medikaments X umfasst. Die Entsch\u00e4digung betr\u00e4gt Hryvnia und wir garantieren den strengen Schutz Ihrer Daten. Senden Sie Ihren Lebenslauf an unsere sichere 3CuqhtN4aPRTfp9VzwhPVe6EgeXjFx9.",
      "expected": "CUSTOMER_DATA",
      "source": "Isotonic/pii-masking-200k",
      "pii_types": [
        "ADDRESS",
        "NAME"
      ]
    },
    {
      "text": "Ehi, volevo solo farti sapere che il pagamento per accedere alla nostra piattaforma di apprendimento non \u00e8 andato a buon fine. Potrebbe essere un errore con i dettagli di pagamento del numero di conto 71181181 o della carta di credito 4936208585187903 che hai fornito?",
      "expected": "NONE",
      "source": "Isotonic/pii-masking-200k",
      "pii_types": []
    },
    {
      "text": "Liebes Team, gem\u00e4\u00df Martinique erfordert das Projekt, dass wir die Netzwerkverbindung bei 253.16.152.13 auf potenziell sch\u00e4dlichen Datenverkehr hin genau \u00fcberwachen.",
      "expected": "NONE",
      "source": "Isotonic/pii-masking-200k",
      "pii_types": []
    },
    {
      "text": "In der N\u00e4he von [6.3904,119.1596] wurde ein neuer Virusstamm entdeckt. Die \u00f6rtlichen Gesundheitsbeh\u00f6rden im Southwest arbeiten unerm\u00fcdlich daran, den Ausbruch einzud\u00e4mmen.",
      "expected": "NONE",
      "source": "Isotonic/pii-masking-200k",
      "pii_types": []
    },
    {
      "text": "Les voitures de soci\u00e9t\u00e9 sont-elles impos\u00e9es diff\u00e9remment ? Je viens de recevoir un nouveau v\u00e9hicule avec son num\u00e9ro d'immatriculation (VRM) DD89NAU. Je r\u00e9side actuellement dans le code postal 25752.",
      "expected": "NONE",
      "source": "Isotonic/pii-masking-200k",
      "pii_types": []
    },
    {
      "text": "Il nostro programma di formazione in British Columbia inizia puntualmente alle 11:45 AM. Ricorda, \u00e8 importante rispettare i tempi.",
      "expected": "NONE",
      "source": "Isotonic/pii-masking-200k",
      "pii_types": []
    },
    {
      "text": "Les frais du programme peuvent \u00eatre facilement pay\u00e9s avec la carte \u00e9mise par mastercard, portant le num\u00e9ro de carte 7124893695423682.",
      "expected": "NONE",
      "source": "Isotonic/pii-masking-200k",
      "pii_types": []
    },
    {
      "text": "Cher Kristoffer, vous avez planifi\u00e9 une consultation pour une vasectomie le 17th March, paiement depuis 0xc9ddae4bac3efa1a91ce267ff4e32bce4b73d9aa confirm\u00e9.",
      "expected": "CUSTOMER_DATA",
      "source": "Isotonic/pii-masking-200k",
      "pii_types": [
        "ADDRESS",
        "NAME"
      ]
    },
    {
      "text": "Tutte le regole e le linee guida sopra citate sono progettate tenendo presenti sia i professionisti che i pazienti. Ricordare dettagli come 40:c7:66:f8:9a:9c non \u00e8 un prerequisito, ma seguire le politiche sanitarie e mantenere la riservatezza dei dati chiave come i numeri di PIN (8838), i numeri di SSN (893 77 6440) e i CVV delle carte di credito (931) lo \u00e8.",
      "expected": "CUSTOMER_DATA",
      "source": "Isotonic/pii-masking-200k",
      "pii_types": [
        "SSN"
      ]
    },
    {
      "text": "I nostri rapporti sono stati preparati dal nostro Associate International Accountability Consultant Mortimer Kohler. Il rapporto pu\u00f2 essere accesso sul nostro sicuro https://steel-excursion.name e richiede una password, x_gkB9zhiUXJ, per accedere.",
      "expected": "CREDENTIALS",
      "source": "Isotonic/pii-masking-200k",
      "pii_types": [
        "PASSWORD",
        "NAME",
        "URL"
      ]
    },
    {
      "text": "As an adult with a job in the Quality, I'm signing up for the Life Skills course. Hope to get an acknowledgment on 247.92.173.232.",
      "expected": "NONE",
      "source": "Isotonic/pii-masking-200k",
      "pii_types": []
    },
    {
      "text": "L'\u00e9quipe de gestion du comportement tiendra une r\u00e9union le 16/06/1992 dans le b\u00e2timent 5261 pour discuter des probl\u00e8mes grandissants des \u00e9l\u00e8ves. La pr\u00e9sence de tous les membres du corps enseignant est obligatoire. Rejoignez-nous pour faire de notre campus un espace plus s\u00fbr.",
      "expected": "CUSTOMER_DATA",
      "source": "Isotonic/pii-masking-200k",
      "pii_types": [
        "DATE"
      ]
    },
    {
      "text": "We respect the confidentiality of our participants and their privacy will be maintained. If you wish to remain anonymous during the session, please use the passcode FYiECEudt5m3. For the secure transmission of this passcode, may we suggest using our secure message service located at 209.13.253.18?",
      "expected": "CREDENTIALS",
      "source": "Isotonic/pii-masking-200k",
      "pii_types": [
        "PASSWORD"
      ]
    },
    {
      "text": "The file attached contains our recent transactions from our Business Account 23148157. Please take note of the bank certificate and the remaining balance of K\u010d775749.06.",
      "expected": "NONE",
      "source": "Isotonic/pii-masking-200k",
      "pii_types": []
    },
    {
      "text": "Wir freuen uns, eine gemeinsame Venture mit Marvin - Blick zur Verbesserung unserer medizinischen Schulungsmodule bekannt zu geben. F\u00fcr weitere Informationen senden Sie bitte eine E-Mail an Lacy_Wilderman82@gmail.com.",
      "expected": "CUSTOMER_DATA",
      "source": "Isotonic/pii-masking-200k",
      "pii_types": [
        "NAME",
        "EMAIL"
      ]
    },
    {
      "text": "Shayna Micah, a 55 years Androgynous hailing from the Northeast, has shown tremendous improvement in the program. She could achieve this with consistent effort and the proper use of tools provided. Connect us at 09-795797-288349-5 for the tools.",
      "expected": "CUSTOMER_DATA",
      "source": "Isotonic/pii-masking-200k",
      "pii_types": [
        "PHONE",
        "NAME"
      ]
    },
    {
      "text": "Wir haben einen Anstieg der Infektionsrate in [-28.0285,27.574] festgestellt. Unser Callcenter ben\u00f6tigt Zugang zur privaten Datenbank mit dem Token OwOctFvUFccT.",
      "expected": "CREDENTIALS",
      "source": "Isotonic/pii-masking-200k",
      "pii_types": [
        "PASSWORD"
      ]
    },
    {
      "text": "Proteggere le informazioni personali come 1951-10-18T09:22:51.065Z 27 years old Male Eye color: Grey 193 cm \u00e8 importante nei forum online per evitare il furto di identit\u00e0.",
      "expected": "NONE",
      "source": "Isotonic/pii-masking-200k",
      "pii_types": []
    },
    {
      "text": "Il nostro ufficio legale ha valutato la posizione della nostra azienda nel Washington County. Richiedono dettagli sulla nostra attivit\u00e0 internazionale. Ti preghiamo di indirizzare queste informazioni a 0x50cfeca4f0d8dca8782ed25f06c5c0db3fa7a0e1.",
      "expected": "CUSTOMER_DATA",
      "source": "Isotonic/pii-masking-200k",
      "pii_types": [
        "ADDRESS"
      ]
    },
    {
      "text": "Veuillez confirmer l'utilisation de la carte de cr\u00e9dit 3976017177331459 pour l'achat des vaccins. Veuillez \u00e9galement valider le CVV 191.",
      "expected": "NONE",
      "source": "Isotonic/pii-masking-200k",
      "pii_types": []
    },
    {
      "text": "Puoi garantire la sicurezza dei pagamenti utilizzando il simbolo di valuta $ durante il pagamento dei servizi con la carta che termina con 3147989316273079.",
      "expected": "NONE",
      "source": "Isotonic/pii-masking-200k",
      "pii_types": []
    },
    {
      "text": "Teilnehmer, die mit dem Auto zum Training kommen, verwenden bitte die GPS-Koordinate [-79.2049,156.1014]. Parken Sie Ihr Fahrzeug mit der Fahrzeugidentifikationsnummer (VIN) W1JET9K34HBF82669 im reservierten Bereich.",
      "expected": "NONE",
      "source": "Isotonic/pii-masking-200k",
      "pii_types": []
    },
    {
      "text": "Come leader Lead Data Officer, mi impegno a promuovere l'educazione artistica nella nostra comunit\u00e0. Per le necessit\u00e0 di finanziamento, utilizza il conto bancario collegato a FR33186040107709O8N7149A597. Troverai le mie informazioni sotto ACCOUNT_1. (PASSWORD 2FBCQIKn1o0J). Contattami se hai bisogno di aiuto!",
      "expected": "CREDENTIALS",
      "source": "Isotonic/pii-masking-200k",
      "pii_types": [
        "IBAN",
        "PASSWORD"
      ]
    },
    {
      "text": "Our online resources for special ed. are accessible at 72ab:76a4:f2a8:eb7c:3cd1:e5c5:814d:0d70 between 10:00am to 1:30pm.",
      "expected": "NONE",
      "source": "Isotonic/pii-masking-200k",
      "pii_types": []
    },
    {
      "text": "Tagga i rapporti di emergenza su [-56.1869,32.1495] con 74-013726-247175-3. Invia via email a 59193372.",
      "expected": "CUSTOMER_DATA",
      "source": "Isotonic/pii-masking-200k",
      "pii_types": [
        "PHONE"
      ]
    },
    {
      "text": "Kayli, wir melden Sie f\u00fcr den globalen Gesundheitsgipfel an. Ihre zugewiesenen Verbindungsdetails lauten Mozilla/5.0 (Macintosh; Intel Mac OS X 10_10_3 rv:3.0; CE) AppleWebKit/533.2.0 (KHTML, like Gecko) Version/4.1.6 Safari/533.2.0 und ad:3f:31:b6:4e:1d. Die Konferenzgeb\u00fchr betr\u00e4gt \u0440\u0443\u0431Gibraltar Pound. F\u00fcgen Sie PVJGTCKB13V f\u00fcr reibungslose Transaktion hinzu.",
      "expected": "CUSTOMER_DATA",
      "source": "Isotonic/pii-masking-200k",
      "pii_types": [
        "NAME"
      ]
    },
    {
      "text": "Arne, veuillez v\u00e9rifier le document de gestion de la propri\u00e9t\u00e9 intellectuelle envoy\u00e9 \u00e0 Neal_Murazik@yahoo.com. Utilisez le code 8114 pour la v\u00e9rification du document.",
      "expected": "CUSTOMER_DATA",
      "source": "Isotonic/pii-masking-200k",
      "pii_types": [
        "NAME",
        "EMAIL"
      ]
    },
    {
      "text": "Rick, be aware of our location committee meeting. It's at these coordinates: [4.2215,-132.244]. It's towards the Northeast.",
      "expected": "CUSTOMER_DATA",
      "source": "Isotonic/pii-masking-200k",
      "pii_types": [
        "NAME"
      ]
    },
    {
      "text": "Le paiement des tests g\u00e9n\u00e9tiques doit \u00eatre effectu\u00e9 \u00e0 notre adresse Litecoin: MN3PVzGuG6obVep6fEvqEQQ3Q63Bz. Le taux de change actuel pour Yemeni Rial est disponible.",
      "expected": "CUSTOMER_DATA",
      "source": "Isotonic/pii-masking-200k",
      "pii_types": [
        "ADDRESS",
        "NAME"
      ]
    },
    {
      "text": "Une radiographie est n\u00e9cessaire pour Mazie, Female. Son nom de compte d'assurance est Savings Account. Contactez-le au 8128760363676472, Wyoming.",
      "expected": "CUSTOMER_DATA",
      "source": "Isotonic/pii-masking-200k",
      "pii_types": [
        "NAME"
      ]
    },
    {
      "text": "Directive de la part de Supervisor : Toutes les informations des patients telles que leur 08/09/2004, leur 756.7474.4363 et leur 38477032 doivent \u00eatre stock\u00e9es de mani\u00e8re s\u00e9curis\u00e9e et ne doivent en aucun cas \u00eatre divulgu\u00e9es.",
      "expected": "CUSTOMER_DATA",
      "source": "Isotonic/pii-masking-200k",
      "pii_types": [
        "SSN"
      ]
    },
    {
      "text": "We're updating our education policies. Connect with Derick upon your earliest convenience at the coordinates [-29.5061,-94.8399]. Thank you.",
      "expected": "CUSTOMER_DATA",
      "source": "Isotonic/pii-masking-200k",
      "pii_types": [
        "NAME"
      ]
    },
    {
      "text": "Cher Dr., les matchs de football de votre enfant pour cette saison auront lieu tous les vendredis et samedis au complexe sportif du 578.",
      "expected": "NONE",
      "source": "Isotonic/pii-masking-200k",
      "pii_types": []
    },
    {
      "text": "National Infrastructure Engineer, les pauses pour les \u00e9l\u00e8ves en \u00e9ducation sp\u00e9cialis\u00e9e doivent \u00eatre mises \u00e0 jour dans le syst\u00e8me. De plus, y a-t-il des mises \u00e0 jour pr\u00e9vues concernant l'accessibilit\u00e9 web dans Brand?",
      "expected": "NONE",
      "source": "Isotonic/pii-masking-200k",
      "pii_types": []
    },
    {
      "text": "Le spese per l'intervento chirurgico possono essere pagate presso la nostra reception. Accettiamo pagamenti effettuati tramite carta di credito jcb numero 2301018721582521. Si prega di notare che il CVV per la transazione sar\u00e0 847.",
      "expected": "NONE",
      "source": "Isotonic/pii-masking-200k",
      "pii_types": []
    },
    {
      "text": "Unsere neue Studie zur Entwicklungspsychologie konzentriert sich auf Intersex man Jugendliche im Alter von ca. 22 years old Jahren. Finden Sie den ausf\u00fchrlichen Bericht unter Bitcoin-Adresse: 3TWm1ngDRKDhtTyLFvUVTFh5kkkdAZJUj.",
      "expected": "CUSTOMER_DATA",
      "source": "Isotonic/pii-masking-200k",
      "pii_types": [
        "ADDRESS"
      ]
    },
    {
      "text": "Access your individual student exchange program portal using password 0otMPkreaLdk and keep track of your progress! We recommend using Opera/12.56 (Macintosh; Intel Mac OS X 10.9.9 U; PT Presto/2.9.162 Version/12.00) browser for the best experience. Mail us for any assistance at Lucious_Gibson91@yahoo.com.",
      "expected": "CREDENTIALS",
      "source": "Isotonic/pii-masking-200k",
      "pii_types": [
        "PASSWORD",
        "EMAIL"
      ]
    },
    {
      "text": "An urgent discussion needs to be held regarding the latest environmental law in Missouri. Let's discuss via 1cd5:cb83:d770:3e25:cdbb:21ef:03de:cbb6.",
      "expected": "NONE",
      "source": "Isotonic/pii-masking-200k",
      "pii_types": []
    },
    {
      "text": "Mrs. Kohler-Padberg doit passer une imagerie de sa cheville. Veuillez envoyer les informations de son rendez-vous \u00e0 sa IPV4 235.211.96.59.",
      "expected": "CUSTOMER_DATA",
      "source": "Isotonic/pii-masking-200k",
      "pii_types": [
        "NAME"
      ]
    },
    {
      "text": "Patient Estevan wurde mit dem Krankenwagen von Suite 900 in die Notaufnahme gebracht und um 23:19 empfangen. Er zeigt Symptome eines Schlaganfalls. Sofortige Aufmerksamkeit erforderlich.",
      "expected": "CUSTOMER_DATA",
      "source": "Isotonic/pii-masking-200k",
      "pii_types": [
        "ADDRESS",
        "NAME"
      ]
    },
    {
      "text": "Bonjour Mariela, veuillez mettre \u00e0 jour votre mot de passe du syst\u00e8me de gestion des feuilles de temps Dolh90Hr6qf4 et votre num\u00e9ro de carte de cr\u00e9dit 8958783464409876 \u00e0 des fins de remboursement.",
      "expected": "CREDENTIALS",
      "source": "Isotonic/pii-masking-200k",
      "pii_types": [
        "PASSWORD",
        "NAME"
      ]
    },
    {
      "text": "\"District Brand Orchestrator, we have noticed a discrepancy in our inventory records and need your immediate attention. Please login to the system using your username Keegan_Hettinger3 and correct it immediately.\",",
      "expected": "CUSTOMER_DATA",
      "source": "Isotonic/pii-masking-200k",
      "pii_types": [
        "USERNAME",
        "NAME"
      ]
    },
    {
      "text": "La prochaine conf\u00e9rence sur '\u00c9coles publiques vs \u00c9coles priv\u00e9es' aura lieu dans la salle de conf\u00e9rence Apt. 903. Les frais d'inscription s'\u00e9l\u00e8vent \u00e0 \u043c\u0430\u043d50, \u00e0 payer \u00e0 IE070G5380054400481056.",
      "expected": "CUSTOMER_DATA",
      "source": "Isotonic/pii-masking-200k",
      "pii_types": [
        "IBAN",
        "ADDRESS"
      ]
    },
    {
      "text": "If you receive an email asking for your parents' american_express card 2278518535913780, never give it out. Also, remember not to give your date of birth (1987-11-27T14:34:47.361Z) as it can be misused.",
      "expected": "NONE",
      "source": "Isotonic/pii-masking-200k",
      "pii_types": []
    },
    {
      "text": "The palliative care team is coordinating a home visit for Lee in 76448, Marche next week. For further details, please contact the team at 09.48-67 61 36.",
      "expected": "CUSTOMER_DATA",
      "source": "Isotonic/pii-masking-200k",
      "pii_types": [
        "PHONE",
        "NAME"
      ]
    },
    {
      "text": "Usa sempre metodi sicuri quando richiesto per transazioni online e non condividere mai dettagli sensibili come la tua carta visa o K941594",
      "expected": "NONE",
      "source": "Isotonic/pii-masking-200k",
      "pii_types": []
    },
    {
      "text": "Le iniziative STEM nella nostra scuola stanno procedendo molto bene in questo trimestre. Solo un promemoria per aggiornare i documenti del team e le spese utilizzando il seguente account 9824914440353940, 785 prima del 7/87.",
      "expected": "NONE",
      "source": "Isotonic/pii-masking-200k",
      "pii_types": []
    },
    {
      "text": "Hallo, hier spricht Guy. Als Reaktion auf die regionale Gesundheitspolitik sind wir der Meinung, dass die Datenverschl\u00fcsselung die Hauptfunktion f\u00fcr alle medizinischen Aufzeichnungen sein sollte. Bitte untersuchen Sie IPV6-Adressen wie 4c3d:dddc:1c83:a1fc:0486:c452:ab5e:bf1d auf m\u00f6gliche Sicherheitsverletzungen.",
      "expected": "CUSTOMER_DATA",
      "source": "Isotonic/pii-masking-200k",
      "pii_types": [
        "NAME"
      ]
    },
    {
      "text": "Cisgender male, il tuo account per l'abbonamento ai materiali di studio \u00e8 stato creato. Utilizza 76053889 per effettuare transazioni. Buono studio!",
      "expected": "NONE",
      "source": "Isotonic/pii-masking-200k",
      "pii_types": []
    },
    {
      "text": "Aurelie10 a montr\u00e9 une am\u00e9lioration acad\u00e9mique constante ce semestre, et son comportement a \u00e9galement \u00e9t\u00e9 exceptionnel. Veuillez transmettre ses progr\u00e8s \u00e0 son tuteur, Ms. Huel, par e-mail \u00e0 Jakayla75@gmail.com.",
      "expected": "CUSTOMER_DATA",
      "source": "Isotonic/pii-masking-200k",
      "pii_types": [
        "USERNAME",
        "NAME",
        "EMAIL"
      ]
    },
    {
      "text": "Grande nouvelle ! Vous avez \u00e9t\u00e9 s\u00e9lectionn\u00e9(e) pour notre programme de mentorat. Veuillez confirmer vos informations : Nom - Courtney Nitzsche, \u00c2ge - 64 years old, Sexe - Female.",
      "expected": "CUSTOMER_DATA",
      "source": "Isotonic/pii-masking-200k",
      "pii_types": [
        "NAME"
      ]
    },
    {
      "text": "Der Cashflow f\u00fcr das Konto 10204287 mit dem Namen Checking Account erscheint unregelm\u00e4\u00dfig. Der Kontostand ist unerwartet um \u20a80.0b gestiegen. K\u00f6nnten Sie das \u00fcberpr\u00fcfen?",
      "expected": "CUSTOMER_DATA",
      "source": "Isotonic/pii-masking-200k",
      "pii_types": [
        "NAME"
      ]
    },
    {
      "text": "\u00c9tudiants, rejoignez-nous ce vendredi pour une th\u00e9rapie de bien-\u00eatre. M\u00eame les personnes de 31 ans ont trouv\u00e9 cela utile. Connectez-vous avec l'IP fournie : cdcd:9b86:9fef:d8d6:a5fb:afed:ff5c:5cec",
      "expected": "NONE",
      "source": "Isotonic/pii-masking-200k",
      "pii_types": []
    },
    {
      "text": "Trendige Gesundheitspolitiken weltweit zeigen eine Neigung zu geschlechtsspezifischen Gesundheitsma\u00dfnahmen, wobei einige Initiativen f\u00fcr Male priorisiert werden. Ich fordere unsere Assistant auf, unsere eigenen Richtlinien in dieser Hinsicht sorgf\u00e4ltig zu \u00fcberpr\u00fcfen.",
      "expected": "NONE",
      "source": "Isotonic/pii-masking-200k",
      "pii_types": []
    },
    {
      "text": "Ciao Newell, il tuo impegno come tutor di matematica non \u00e8 passato inosservato. Siamo lieti di premiarti con un bonus in Bitcoin. Dovresti vedere il bonus sul tuo account con l'indirizzo Bitcoin 3hwtDA4E12v3bqYZeHQwM8SGrKL7q8ZgcGAEUES.",
      "expected": "CUSTOMER_DATA",
      "source": "Isotonic/pii-masking-200k",
      "pii_types": [
        "ADDRESS",
        "NAME"
      ]
    },
    {
      "text": "Derick, avez-vous re\u00e7u les bulletins dermatologiques via Newton_Lubowitz@gmail.com?",
      "expected": "CUSTOMER_DATA",
      "source": "Isotonic/pii-masking-200k",
      "pii_types": [
        "NAME",
        "EMAIL"
      ]
    },
    {
      "text": "Fantastic job by our oncology team and Jaden, the Lead Paradigm Executive. Please note the details of our upcoming meeting are on the server with IP address 7bbc:ca96:cced:0f86:ea65:b50b:d133:43a6. The password for the file is yWpAynp6ji8u.",
      "expected": "CREDENTIALS",
      "source": "Isotonic/pii-masking-200k",
      "pii_types": [
        "PASSWORD",
        "NAME"
      ]
    },
    {
      "text": "L'\u00c9cole Feil Gateway recherche de l'aide sous forme de Peso Uruguayo. Envoyez des dons \u00e0 l'adresse GL1933834015351793.",
      "expected": "CUSTOMER_DATA",
      "source": "Isotonic/pii-masking-200k",
      "pii_types": [
        "IBAN"
      ]
    },
    {
      "text": "Caro Lenna, grazie per la prenotazione dell'appuntamento il 10/87 per tuo figlio e per aver scelto la nostra unit\u00e0 di cura pediatrica. Potresti condividere alcuni dettagli riguardanti eventuali problemi di vista connessi all'occhio che tuo figlio potrebbe avere? Il colore degli occhi di tuo figlio - green",
      "expected": "CUSTOMER_DATA",
      "source": "Isotonic/pii-masking-200k",
      "pii_types": [
        "DATE",
        "NAME"
      ]
    },
    {
      "text": "Cher Corine, y a-t-il de nouvelles recherches disponibles sur les m\u00e9thodes d'enseignement pour l'\u00e9ducation sp\u00e9ciale dans le Pike County ?",
      "expected": "CUSTOMER_DATA",
      "source": "Isotonic/pii-masking-200k",
      "pii_types": [
        "NAME"
      ]
    },
    {
      "text": "En raison de la hausse des cas de maladies infectieuses dans le quartier 38108, nous vous serions reconnaissants d'effectuer un paiement de Rp1000 sur votre compte Credit Card Account.",
      "expected": "CUSTOMER_DATA",
      "source": "Isotonic/pii-masking-200k",
      "pii_types": [
        "NAME"
      ]
    },
    {
      "text": "Secondo la nuova legge fiscale, le transazioni dal conto Money Market Account numero 68220125 a 31S6Ai5ZP2VSLpmvWXfeApbkDgb6hm94Dit3AsbD sono soggette a tassazione. Si prega di fornire la password VAcGs8f4cP7X e di chiamarmi al numero 086.7433211.",
      "expected": "CREDENTIALS",
      "source": "Isotonic/pii-masking-200k",
      "pii_types": [
        "PHONE",
        "PASSWORD",
        "ADDRESS",
        "NAME"
      ]
    },
    {
      "text": "Invitation to Arlo for inaugural session on endocrine disorders. Your confidential login details are - Investment Account, and Password - xpDJQsc3zKCd.",
      "expected": "CREDENTIALS",
      "source": "Isotonic/pii-masking-200k",
      "pii_types": [
        "PASSWORD",
        "NAME"
      ]
    },
    {
      "text": "Sehr geehrter Hilario, wir haben eine verd\u00e4chtige Aktivit\u00e4t unter Verwendung von Mozilla/5.0 (Macintosh; U; PPC Mac OS X 10_9_6)  AppleWebKit/535.1.1 (KHTML, like Gecko) Chrome/20.0.872.0 Safari/535.1.1 von Ihrem Konto festgestellt. Wenn es nicht Sie sind, kontaktieren Sie uns bitte.",
      "expected": "CUSTOMER_DATA",
      "source": "Isotonic/pii-masking-200k",
      "pii_types": [
        "NAME"
      ]
    },
    {
      "text": "Accedi al curriculum digitalmente utilizzando un computer con indirizzo MAC fc:60:50:6b:36:e2. I dettagli per l'accesso sono stati inviati via email a Darien75@gmail.com con la password c_1mOzZGlPsm. Ignora richieste provenienti da indirizzi IP diversi. Verifica con il nostro IP corrente acfc:aa8f:dcdd:96fe:c6bf:0ae0:cf1d:fded.",
      "expected": "CREDENTIALS",
      "source": "Isotonic/pii-masking-200k",
      "pii_types": [
        "PASSWORD",
        "EMAIL"
      ]
    },
    {
      "text": "Salut Bailey, c'est urgent ! Notre \u00e9quipe Director a besoin du rapport d'analyse pour les comptes commen\u00e7ant par 1636610643308471 dans l'\u00c9tat de Sachsen. Nous avons constat\u00e9 des divergences dans les adresses IP (219.103.6.180, 82dd:e54c:58d9:a0db:ca70:9ffb:5aef:23ec).",
      "expected": "CUSTOMER_DATA",
      "source": "Isotonic/pii-masking-200k",
      "pii_types": [
        "NAME"
      ]
    },
    {
      "text": "Our payment gateway has encountered an issue with your visa mastercard. We kindly ask you to check if the associated CVV 036 is correct.",
      "expected": "NONE",
      "source": "Isotonic/pii-masking-200k",
      "pii_types": []
    },
    {
      "text": "Avviso di sicurezza: Tentativo di accesso da 2bf4:9fa1:5a1f:31ab:d5ea:77a1:14cf:82d7 nell'unit\u00e0 di terapia intensiva Suite 522. Reparto IT, vi preghiamo di investigare.",
      "expected": "CUSTOMER_DATA",
      "source": "Isotonic/pii-masking-200k",
      "pii_types": [
        "ADDRESS"
      ]
    },
    {
      "text": "Parent-Teacher meet-up scheduled for the 23rd January. Here's the zoom link and password: 4123074361961837 and 1vOkNuyN6MsJ",
      "expected": "CREDENTIALS",
      "source": "Isotonic/pii-masking-200k",
      "pii_types": [
        "PASSWORD"
      ]
    },
    {
      "text": "Le co\u00fbt de la vaccination en Falkland Islands Pound est largement couvert par votre assurance 8195160796905427 \u00e9mise par american_express.",
      "expected": "NONE",
      "source": "Isotonic/pii-masking-200k",
      "pii_types": []
    },
    {
      "text": "Dear Olson, remember to take time for self-care and practice the coping techniques we discussed. Also note that payment for our sessions can be made to the account named Money Market Account with account number: 57682814.",
      "expected": "CUSTOMER_DATA",
      "source": "Isotonic/pii-masking-200k",
      "pii_types": [
        "NAME"
      ]
    },
    {
      "text": "F\u00fcr erbrachte Gesundheitsdienstleistungen werden Ihnen P-Betrag in Rechnung gestellt. Sie k\u00f6nnen \u00fcber 7118820525803352 bezahlen. Bei Fragen zur Verwaltung chronischer Krankheiten k\u00f6nnen Sie sich gerne an uns wenden.",
      "expected": "NONE",
      "source": "Isotonic/pii-masking-200k",
      "pii_types": []
    },
    {
      "text": "Liebe(r) Marshall, wir freuen uns, Ihnen mitteilen zu k\u00f6nnen, dass Ihr Termin f\u00fcr den December 21, 1986 best\u00e4tigt ist. Bei \u00c4nderungen bitten wir um fr\u00fchestm\u00f6gliche Benachrichtigung.",
      "expected": "CUSTOMER_DATA",
      "source": "Isotonic/pii-masking-200k",
      "pii_types": [
        "DATE",
        "NAME"
      ]
    },
    {
      "text": "Male, vos r\u00e9sultats de test seront envoy\u00e9s \u00e0 Newell7@yahoo.com. En cas d'urgence, nous vous contacterons via 77-916844-416255-0 et si nous ne parvenons pas \u00e0 vous joindre, nous disposons de votre adresse de contact secondaire Suite 100. Nous prenons votre vie priv\u00e9e au s\u00e9rieux.",
      "expected": "CUSTOMER_DATA",
      "source": "Isotonic/pii-masking-200k",
      "pii_types": [
        "PHONE",
        "ADDRESS",
        "EMAIL"
      ]
    },
    {
      "text": "Intersex, ricorda di portare il VIN CVAPF3FYSBM863617 per il veicolo parcheggiato in garage durante il tuo pernottamento per i test.",
      "expected": "NONE",
      "source": "Isotonic/pii-masking-200k",
      "pii_types": []
    },
    {
      "text": "Apr\u00e8s avoir analys\u00e9 les donn\u00e9es, les \u00e9coles priv\u00e9es pr\u00e9sentent des performances sup\u00e9rieures. La p\u00e9riode de collecte des donn\u00e9es s'est termin\u00e9e \u00e0 13. Veuillez consulter notre rapport en ligne en visitant 73.56.176.101.",
      "expected": "NONE",
      "source": "Isotonic/pii-masking-200k",
      "pii_types": []
    },
    {
      "text": "Arvid Lebsack, deine praktischen Aufgaben heben sich in Web hervor. Die Website des Colleges https://medium-loyalty.name hat deine Beitr\u00e4ge ver\u00f6ffentlicht.",
      "expected": "CUSTOMER_DATA",
      "source": "Isotonic/pii-masking-200k",
      "pii_types": [
        "NAME",
        "URL"
      ]
    },
    {
      "text": "Nuova tecnologia diagnostica proveniente da Surrey mostra un notevole miglioramento nei tempi di scansione. 4 years old di prove mostrano un feedback positivo. Il lancio \u00e8 previsto per 5 PM.",
      "expected": "NONE",
      "source": "Isotonic/pii-masking-200k",
      "pii_types": []
    },
    {
      "text": "Comme convenu lors de notre discussion, la Infrastructure est externalis\u00e9e. Autorisation de connexion sur ce https://hollow-radar.info/ avec les identifiants Kaden.Monahan96 et VFvzMt_ZHQMI.",
      "expected": "CREDENTIALS",
      "source": "Isotonic/pii-masking-200k",
      "pii_types": [
        "USERNAME",
        "PASSWORD",
        "NAME",
        "URL"
      ]
    },
    {
      "text": "A tutti gli studenti: La corretta gestione del tempo aiuta anche nel tuo ruolo di Legacy Assurance Director. Contatta il tuo consulente accademico tramite Opera/10.59 (X11; Linux x86_64; U; VI Presto/2.9.189 Version/11.00) per consigli e trucchi.",
      "expected": "NONE",
      "source": "Isotonic/pii-masking-200k",
      "pii_types": []
    },
    {
      "text": "Informierte Zustimmung bedeutet, dass keine pers\u00f6nlich identifizierbaren Informationen preisgegeben werden. Daher sind die pers\u00f6nlichen Daten der Teilnehmer f\u00fcr unsere Studie mit Tokens wie 67386 und Cavendish Road maskiert. Bitte richten Sie alle Anfragen an den Forschungsleiter unter fc9c:13fe:3b30:70a8:d6aa:09f3:ab27:5ffe.",
      "expected": "NONE",
      "source": "Isotonic/pii-masking-200k",
      "pii_types": []
    },
    {
      "text": "Mise \u00e0 jour des donn\u00e9es requise pour le patient enregistr\u00e9 sous le num\u00e9ro de compte 38598427. Sa derni\u00e8re visite remonte au 26th October.",
      "expected": "NONE",
      "source": "Isotonic/pii-masking-200k",
      "pii_types": []
    },
    {
      "text": "Female October 8, 1914 wurde in einem kritischen Zustand in die Intensivstation aufgenommen. Das aktuelle Team ben\u00f6tigt die 4c:b1:b7:bb:86:d2-Adresse, um die erforderlichen Gesundheitsakten mit Suite 620 zu teilen. Bitte teilen Sie diese zeitnah mit.",
      "expected": "CUSTOMER_DATA",
      "source": "Isotonic/pii-masking-200k",
      "pii_types": [
        "ADDRESS"
      ]
    },
    {
      "text": "15. A local NGO donated \u20a84769742378291670 to support the Early Childhood Education project in Madalineton.",
      "expected": "NONE",
      "source": "Isotonic/pii-masking-200k",
      "pii_types": []
    },
    {
      "text": "4. Assurez-vous de r\u00e9server du temps pour revoir vos cours en ligne. N'oubliez pas de vous connecter en utilisant votre Kennedi36 et votre uK1b9_nUj2nO pour le portail \u00e9tudiant sur https://bouncy-ceramics.org.",
      "expected": "CREDENTIALS",
      "source": "Isotonic/pii-masking-200k",
      "pii_types": [
        "USERNAME",
        "PASSWORD",
        "NAME",
        "URL"
      ]
    },
    {
      "text": "La psico-oncologia \u00e8 l'intersezione degli aspetti fisici, psicologici, sociali e comportamentali dell'esperienza del cancro sia per i pazienti che per le loro famiglie. Con il consenso del paziente, raccogliamo e analizziamo dati personali come 30 years old, Male to female transgender woman e 1/72 per fornire una migliore assistenza.",
      "expected": "NONE",
      "source": "Isotonic/pii-masking-200k",
      "pii_types": []
    },
    {
      "text": "Liebe Two-spirit person, Ihr aktueller Standort [75.3119,89.6542] unterscheidet sich von Ihrem letzten Login. Bitte best\u00e4tigen Sie, ob dies korrekt ist. Wir m\u00f6chten Ihre Sicherheit gew\u00e4hrleisten.",
      "expected": "NONE",
      "source": "Isotonic/pii-masking-200k",
      "pii_types": []
    },
    {
      "text": "Le rendez-vous de suivi pour Miss Rachelle Elliott Carroll, sexe Transexual male, est pr\u00e9vu pour le 11/76 \u00e0 2 AM. Ses principales pr\u00e9occupations incluent une augmentation du nombre d'imperfections et une peau constamment s\u00e8che.",
      "expected": "CUSTOMER_DATA",
      "source": "Isotonic/pii-masking-200k",
      "pii_types": [
        "DATE",
        "NAME"
      ]
    },
    {
      "text": "Das NO1170100051604 Konto wird f\u00fcr Ihre anstehende Operation belastet, die im Southeast Fl\u00fcgel unseres Krankenhauses geplant ist. Ihr An\u00e4sthesist wird ein Profi mit gr\u00fcnen Eye color: Green wie Ihren sein.",
      "expected": "CUSTOMER_DATA",
      "source": "Isotonic/pii-masking-200k",
      "pii_types": [
        "IBAN"
      ]
    },
    {
      "text": "La nostra prossima sessione di terapia familiare con te e Carol potrebbe essere uno spazio per discutere strategie per risolvere dispute che sorgono a causa di questioni come l'uso della carta di credito 2663671650942324.",
      "expected": "CUSTOMER_DATA",
      "source": "Isotonic/pii-masking-200k",
      "pii_types": [
        "NAME"
      ]
    },
    {
      "text": "Ms. Shirley Zboncak's Notizen: Lernsitzung am 5/23, Versuche abstrakte Konzepte zu beherrschen. Zeit: 2 PM.",
      "expected": "CUSTOMER_DATA",
      "source": "Isotonic/pii-masking-200k",
      "pii_types": [
        "DATE",
        "NAME"
      ]
    },
    {
      "text": "Hey Blaze, we detected a possible intrusion into our systems from IP 71.30.39.4. Please verify and protect all patient data, particularly the ones related to our medical imaging sector.",
      "expected": "CUSTOMER_DATA",
      "source": "Isotonic/pii-masking-200k",
      "pii_types": [
        "NAME"
      ]
    },
    {
      "text": "Per favore, condividete questa notizia sulla campagna di vaccinazione con i vostri contatti di et\u00e0 superiore ai 96 anni. Il nostro centro di vaccinazione si trova presso il 61974 in Cavendish Road. Accettiamo pagamenti online tramite 7229370843991582.",
      "expected": "NONE",
      "source": "Isotonic/pii-masking-200k",
      "pii_types": []
    },
    {
      "text": "Per favore, consulta il nostro team a 99415-4101. Stanno avendo problemi con il software (Opera/12.31 (Windows NT 5.1; U; SR Presto/2.9.171 Version/11.00)).",
      "expected": "NONE",
      "source": "Isotonic/pii-masking-200k",
      "pii_types": []
    },
    {
      "text": "Hallo Hailie, wir freuen uns, Ihnen einen neuen Lebenskompetenzkurs bei Weber - Boyle vorstellen zu d\u00fcrfen. Um sich anzumelden, \u00fcberweisen Sie bitte die Kursgeb\u00fchr an folgende 3jfySpLaEtP9hAMAeDiBeyFCrs.",
      "expected": "CUSTOMER_DATA",
      "source": "Isotonic/pii-masking-200k",
      "pii_types": [
        "ADDRESS",
        "NAME"
      ]
    },
    {
      "text": "F\u00fcr grenz\u00fcberschreitende Transaktionen stellen Sie bitte sicher, dass die AOA in Lesotho Loti umgerechnet wird, um die Einheitlichkeit unserer Aufzeichnungen zu gew\u00e4hrleisten.",
      "expected": "NONE",
      "source": "Isotonic/pii-masking-200k",
      "pii_types": []
    },
    {
      "text": "Keira79, unser System hat eine verd\u00e4chtige IP-Adresse (147.24.0.208) erkannt, die versucht, auf Ihr Telemedizin-Konto zuzugreifen. Wenn Sie dies nicht waren, setzen Sie bitte Ihr Passwort zur\u00fcck: 0JIZ9khBMrGS.",
      "expected": "CREDENTIALS",
      "source": "Isotonic/pii-masking-200k",
      "pii_types": [
        "USERNAME",
        "PASSWORD",
        "NAME"
      ]
    },
    {
      "text": "Hello, Tomorrow's STEM meetup is at 04881 location. Note - Students traveling by car need to inform us accordingly with their 8AUTTAS927N443248 and permit for parking management. Thank you!",
      "expected": "NONE",
      "source": "Isotonic/pii-masking-200k",
      "pii_types": []
    },
    {
      "text": "J'ai essay\u00e9 de joindre 65-117531-126391-9 pour le bilan de sant\u00e9 pr\u00e9vu aujourd'hui. Veuillez nous contacter au +362.259-249 3342.",
      "expected": "CUSTOMER_DATA",
      "source": "Isotonic/pii-masking-200k",
      "pii_types": [
        "PHONE"
      ]
    },
    {
      "text": "Die Schl\u00fcssel zur Solutions Bildungsfortschritt ist globale Zusammenarbeit. \u00dcberweisen Sie Ihre Beitr\u00e4ge auf das Kontonummer 03574159, BIC - SEMRSGMDUQU.",
      "expected": "NONE",
      "source": "Isotonic/pii-masking-200k",
      "pii_types": []
    },
    {
      "text": "Wir freuen uns, Dr. Labadie, unseren neuen Lehrer mit bemerkenswertem Hintergrund in der fr\u00fchkindlichen Bildung, begr\u00fc\u00dfen zu d\u00fcrfen. Sie wird w\u00e4hrend des Eltern-Lehrer-Treffens in 6802, Enos Gateway sein.",
      "expected": "CUSTOMER_DATA",
      "source": "Isotonic/pii-masking-200k",
      "pii_types": [
        "NAME"
      ]
    },
    {
      "text": "Potresti gentilmente aggiornare il conto del nostro fornitore Denesik, Stanton and Johnson con la nuova indirizzo MAC 18:3b:02:71:a7:a7?",
      "expected": "CUSTOMER_DATA",
      "source": "Isotonic/pii-masking-200k",
      "pii_types": [
        "NAME"
      ]
    },
    {
      "text": "For those who will be traveling for the upcoming project meeting, your travel expenses should be charged to our company account. Please use account number 40387740, associated with our Checking Account.",
      "expected": "CUSTOMER_DATA",
      "source": "Isotonic/pii-masking-200k",
      "pii_types": [
        "NAME"
      ]
    },
    {
      "text": "Dear Grayson, a failed credit card payment notification with card ending 8649512425693921 was initiated on your account for the service charges. Please have the matter addressed at your earliest convenience.",
      "expected": "CUSTOMER_DATA",
      "source": "Isotonic/pii-masking-200k",
      "pii_types": [
        "NAME"
      ]
    },
    {
      "text": "Alerte ! Tous les \u00e9tudiants \u00e2g\u00e9s de 68 de 11432 Beech Close. La campagne de vaccination aura lieu demain. Veuillez \u00eatre pr\u00e9sent.",
      "expected": "NONE",
      "source": "Isotonic/pii-masking-200k",
      "pii_types": []
    },
    {
      "text": "Ecco un promemoria per tutti: assicurarsi che le informazioni come East Travisfurt e 49143-9675 del paziente Carey Schuppe siano confidenziali.",
      "expected": "CUSTOMER_DATA",
      "source": "Isotonic/pii-masking-200k",
      "pii_types": [
        "NAME"
      ]
    },
    {
      "text": "For those having trouble focusing at home, study at the local library. We can arrange a study group on September 4, 1978 if anyone from 24545 is interested.",
      "expected": "CUSTOMER_DATA",
      "source": "Isotonic/pii-masking-200k",
      "pii_types": [
        "DATE"
      ]
    },
    {
      "text": "Ciao! Volevo solo inviarti i dettagli della mia cliente di 1 years old anni. Lei \u00e8 una Male con occhi Hazel e circa 123cm di altezza. Ha seguito il mio piano per un mese adesso e ho notato cambiamenti sorprendenti.",
      "expected": "NONE",
      "source": "Isotonic/pii-masking-200k",
      "pii_types": []
    }
  ]
}